{
	"groups": [
		{
			"keys": "start_bg_png,start_start_png,start_tip_png,start_title_png,start_start_bg_png,progress_bg_png,progress_front_png",
			"name": "start"
		},
		{
			"keys": "game_v_open_png,game_v_close_png,game_tuijian_open_png,game_tuijian_close_png,game_score_png,game_replay_png,game_high_score_png,game_gz_mei_png,game_gz_hong_png,game_gz_hei_png,game_gz_fang_png,game_friend_rank_png,game_change_png,game_bomb_png,game_bg_png,border_png,game_get_png,game_hammer_png,game_game_png,game_panel_png,game_nobomb_png,game_panel_1_png,over_share_png,over_replay_png,close_png,over_friend_rank_png,item_bomb_png,item_change_png,item_share_png,item_watch_png,over_panel_png,click_tip_png",
			"name": "game"
		},
		{
			"keys": "8_mp3,item_change_png,item_bomb_png,item_share_png,item_watch_png,click_tip_png",
			"name": "preload"
		}
	],
	"resources": [
		{
			"url": "assets/CheckBox/checkbox_select_disabled.png",
			"type": "image",
			"name": "checkbox_select_disabled_png"
		},
		{
			"url": "assets/CheckBox/checkbox_select_down.png",
			"type": "image",
			"name": "checkbox_select_down_png"
		},
		{
			"url": "assets/CheckBox/checkbox_select_up.png",
			"type": "image",
			"name": "checkbox_select_up_png"
		},
		{
			"url": "assets/CheckBox/checkbox_unselect.png",
			"type": "image",
			"name": "checkbox_unselect_png"
		},
		{
			"url": "assets/ItemRenderer/selected.png",
			"type": "image",
			"name": "selected_png"
		},
		{
			"url": "assets/Panel/border.png",
			"type": "image",
			"name": "border_png"
		},
		{
			"url": "assets/Panel/header.png",
			"type": "image",
			"name": "header_png"
		},
		{
			"url": "assets/RadioButton/radiobutton_select_disabled.png",
			"type": "image",
			"name": "radiobutton_select_disabled_png"
		},
		{
			"url": "assets/RadioButton/radiobutton_select_down.png",
			"type": "image",
			"name": "radiobutton_select_down_png"
		},
		{
			"url": "assets/RadioButton/radiobutton_select_up.png",
			"type": "image",
			"name": "radiobutton_select_up_png"
		},
		{
			"url": "assets/RadioButton/radiobutton_unselect.png",
			"type": "image",
			"name": "radiobutton_unselect_png"
		},
		{
			"url": "assets/ScrollBar/roundthumb.png",
			"type": "image",
			"name": "roundthumb_png"
		},
		{
			"url": "assets/Slider/thumb.png",
			"type": "image",
			"name": "thumb_png"
		},
		{
			"url": "assets/Slider/track.png",
			"type": "image",
			"name": "track_png"
		},
		{
			"url": "assets/Slider/tracklight.png",
			"type": "image",
			"name": "tracklight_png"
		},
		{
			"url": "assets/ToggleSwitch/handle.png",
			"type": "image",
			"name": "handle_png"
		},
		{
			"url": "assets/ToggleSwitch/off.png",
			"type": "image",
			"name": "off_png"
		},
		{
			"url": "assets/ToggleSwitch/on.png",
			"type": "image",
			"name": "on_png"
		},
		{
			"url": "assets/Button/button_down.png",
			"type": "image",
			"name": "button_down_png"
		},
		{
			"url": "assets/Button/button_up.png",
			"type": "image",
			"name": "button_up_png"
		},
		{
			"url": "assets/ProgressBar/thumb_pb.png",
			"type": "image",
			"name": "thumb_pb_png"
		},
		{
			"url": "assets/ProgressBar/track_pb.png",
			"type": "image",
			"name": "track_pb_png"
		},
		{
			"url": "assets/ScrollBar/track_sb.png",
			"type": "image",
			"name": "track_sb_png"
		},
		{
			"url": "config/description.json",
			"type": "json",
			"name": "description_json"
		},
		{
			"url": "assets/start/start_bg.png",
			"type": "image",
			"name": "start_bg_png"
		},
		{
			"url": "assets/start/start_start.png",
			"type": "image",
			"name": "start_start_png"
		},
		{
			"url": "assets/start/start_tip.png",
			"type": "image",
			"name": "start_tip_png"
		},
		{
			"url": "assets/start/start_title.png",
			"type": "image",
			"name": "start_title_png"
		},
		{
			"url": "assets/game/game_bg.png",
			"type": "image",
			"name": "game_bg_png"
		},
		{
			"url": "assets/game/game_bomb.png",
			"type": "image",
			"name": "game_bomb_png"
		},
		{
			"url": "assets/game/game_change.png",
			"type": "image",
			"name": "game_change_png"
		},
		{
			"url": "assets/game/game_friend_rank.png",
			"type": "image",
			"name": "game_friend_rank_png"
		},
		{
			"url": "assets/game/game_gz_fang.png",
			"type": "image",
			"name": "game_gz_fang_png"
		},
		{
			"url": "assets/game/game_gz_hei.png",
			"type": "image",
			"name": "game_gz_hei_png"
		},
		{
			"url": "assets/game/game_gz_hong.png",
			"type": "image",
			"name": "game_gz_hong_png"
		},
		{
			"url": "assets/game/game_gz_mei.png",
			"type": "image",
			"name": "game_gz_mei_png"
		},
		{
			"url": "assets/game/game_high_score.png",
			"type": "image",
			"name": "game_high_score_png"
		},
		{
			"url": "assets/game/game_replay.png",
			"type": "image",
			"name": "game_replay_png"
		},
		{
			"url": "assets/game/game_score.png",
			"type": "image",
			"name": "game_score_png"
		},
		{
			"url": "assets/game/game_tuijian_close.png",
			"type": "image",
			"name": "game_tuijian_close_png"
		},
		{
			"url": "assets/game/game_tuijian_open.png",
			"type": "image",
			"name": "game_tuijian_open_png"
		},
		{
			"url": "assets/game/game_v_close.png",
			"type": "image",
			"name": "game_v_close_png"
		},
		{
			"url": "assets/game/game_v_open.png",
			"type": "image",
			"name": "game_v_open_png"
		},
		{
			"url": "assets/game/game_get.png",
			"type": "image",
			"name": "game_get_png"
		},
		{
			"url": "assets/game/game_hammer.png",
			"type": "image",
			"name": "game_hammer_png"
		},
		{
			"url": "assets/start/start_start_bg.png",
			"type": "image",
			"name": "start_start_bg_png"
		},
		{
			"url": "assets/game/game_game.png",
			"type": "image",
			"name": "game_game_png"
		},
		{
			"url": "assets/game/game_panel.png",
			"type": "image",
			"name": "game_panel_png"
		},
		{
			"url": "assets/game/game_nobomb.png",
			"type": "image",
			"name": "game_nobomb_png"
		},
		{
			"url": "assets/game/game_panel_1.png",
			"type": "image",
			"name": "game_panel_1_png"
		},
		{
			"url": "assets/game/over_replay.png",
			"type": "image",
			"name": "over_replay_png"
		},
		{
			"url": "assets/game/over_share.png",
			"type": "image",
			"name": "over_share_png"
		},
		{
			"url": "assets/start/progress_front.png",
			"type": "image",
			"name": "progress_front_png"
		},
		{
			"url": "assets/start/progress_bg.png",
			"type": "image",
			"name": "progress_bg_png"
		},
		{
			"url": "assets/game/over_panel.png",
			"type": "image",
			"name": "over_panel_png"
		},
		{
			"url": "assets/game/rank_gold.png",
			"type": "image",
			"name": "rank_gold_png"
		},
		{
			"url": "assets/game/rank_copper.png",
			"type": "image",
			"name": "rank_copper_png"
		},
		{
			"url": "assets/game/rank_silver.png",
			"type": "image",
			"name": "rank_silver_png"
		},
		{
			"url": "assets/game/close.png",
			"type": "image",
			"name": "close_png"
		},
		{
			"url": "assets/game/over_friend_rank.png",
			"type": "image",
			"name": "over_friend_rank_png"
		},
		{
			"url": "sounds/0.mp3",
			"type": "sound",
			"name": "0_mp3"
		},
		{
			"url": "sounds/1.mp3",
			"type": "sound",
			"name": "1_mp3"
		},
		{
			"url": "sounds/10.mp3",
			"type": "sound",
			"name": "10_mp3"
		},
		{
			"url": "sounds/2.mp3",
			"type": "sound",
			"name": "2_mp3"
		},
		{
			"url": "sounds/3.mp3",
			"type": "sound",
			"name": "3_mp3"
		},
		{
			"url": "sounds/4.mp3",
			"type": "sound",
			"name": "4_mp3"
		},
		{
			"url": "sounds/5.mp3",
			"type": "sound",
			"name": "5_mp3"
		},
		{
			"url": "sounds/6.mp3",
			"type": "sound",
			"name": "6_mp3"
		},
		{
			"url": "sounds/7.mp3",
			"type": "sound",
			"name": "7_mp3"
		},
		{
			"url": "sounds/9.mp3",
			"type": "sound",
			"name": "9_mp3"
		},
		{
			"url": "sounds/bgstart.mp3",
			"type": "sound",
			"name": "bgstart_mp3"
		},
		{
			"url": "sounds/disappear.mp3",
			"type": "sound",
			"name": "disappear_mp3"
		},
		{
			"url": "sounds/putdown.mp3",
			"type": "sound",
			"name": "putdown_mp3"
		},
		{
			"url": "sounds/putup.mp3",
			"type": "sound",
			"name": "putup_mp3"
		},
		{
			"url": "sounds/shiban.mp3",
			"type": "sound",
			"name": "shiban_mp3"
		},
		{
			"url": "sounds/8.mp3",
			"type": "sound",
			"name": "8_mp3"
		},
		{
			"url": "assets/game/item_change.png",
			"type": "image",
			"name": "item_change_png"
		},
		{
			"url": "assets/game/item_bomb.png",
			"type": "image",
			"name": "item_bomb_png"
		},
		{
			"url": "assets/game/item_share.png",
			"type": "image",
			"name": "item_share_png"
		},
		{
			"url": "assets/game/item_watch.png",
			"type": "image",
			"name": "item_watch_png"
		},
		{
			"url": "assets/game/click_tip.png",
			"type": "image",
			"name": "click_tip_png"
		}
	]
}